ztjgwz/__init__.py
ztjgwz/etl.py
ztjgwz/excel.py
ztjgwz-0.0.5.dist-info/METADATA
ztjgwz-0.0.5.dist-info/WHEEL
ztjgwz-0.0.5.dist-info/licenses/LICENSE
ztjgwz-0.0.5.dist-info/RECORD
