Metadata-Version: 2.1
Name: ztjgwz
Version: 0.0.5
Summary: some tools
Author-email: xinwen <coderWen@126.com>
License-File: LICENSE
Classifier: License :: OSI Approved :: MIT License
Classifier: Operating System :: OS Independent
Classifier: Programming Language :: Python :: 3
Requires-Python: >=3.7
Requires-Dist: openpyxl==3.1.2
Requires-Dist: pywin32==306
